{
  "info": {
    "name": "Explore With Me - Rating Events Tests",
    "description": "Postman-тесты для проверки функциональности рейтингов (лайки/дизлайки, рейтинг мероприятий и их авторов, сортировка по рейтингу)",
    "schema": "https://schema.getpostman.com/json/collection/v2.1.0/collection.json"
  },
  "item": [
    {
      "name": "Подготовка данных",
      "item": [
        {
          "name": "1. Создание пользователя 1",
          "request": {
            "method": "POST",
            "header": [
              {
                "key": "Content-Type",
                "value": "application/json"
              }
            ],
            "body": {
              "mode": "raw",
              "raw": "{\n    \"email\": \"testuser1@test.com\",\n    \"name\": \"Test User 1\"\n}"
            },
            "url": {
              "raw": "{{baseUrl}}/admin/users",
              "host": ["{{baseUrl}}"],
              "path": ["admin", "users"]
            }
          },
          "response": []
        },
        {
          "name": "2. Создание пользователя 2",
          "request": {
            "method": "POST",
            "header": [
              {
                "key": "Content-Type",
                "value": "application/json"
              }
            ],
            "body": {
              "mode": "raw",
              "raw": "{\n    \"email\": \"testuser2@test.com\",\n    \"name\": \"Test User 2\"\n}"
            },
            "url": {
              "raw": "{{baseUrl}}/admin/users",
              "host": ["{{baseUrl}}"],
              "path": ["admin", "users"]
            }
          },
          "response": []
        },
        {
          "name": "3. Создание пользователя 3",
          "request": {
            "method": "POST",
            "header": [
              {
                "key": "Content-Type",
                "value": "application/json"
              }
            ],
            "body": {
              "mode": "raw",
              "raw": "{\n    \"email\": \"testuser3@test.com\",\n    \"name\": \"Test User 3\"\n}"
            },
            "url": {
              "raw": "{{baseUrl}}/admin/users",
              "host": ["{{baseUrl}}"],
              "path": ["admin", "users"]
            }
          },
          "response": []
        },
        {
          "name": "4. Создание категории",
          "request": {
            "method": "POST",
            "header": [
              {
                "key": "Content-Type",
                "value": "application/json"
              }
            ],
            "body": {
              "mode": "raw",
              "raw": "{\n    \"name\": \"Test Category\"\n}"
            },
            "url": {
              "raw": "{{baseUrl}}/admin/categories",
              "host": ["{{baseUrl}}"],
              "path": ["admin", "categories"]
            }
          },
          "response": []
        },
        {
          "name": "5. Создание события 1 (User 1)",
          "request": {
            "method": "POST",
            "header": [
              {
                "key": "Content-Type",
                "value": "application/json"
              }
            ],
            "body": {
              "mode": "raw",
              "raw": "{\n    \"annotation\": \"Test event 1 annotation for rating testing\",\n    \"category\": 1,\n    \"description\": \"Test event 1 description for rating testing\",\n    \"eventDate\": \"2026-07-23 10:00:00\",\n    \"location\": {\n        \"lat\": 55.7558,\n        \"lon\": 37.6173\n    },\n    \"paid\": false,\n    \"participantLimit\": 0,\n    \"requestModeration\": false,\n    \"title\": \"Test Event 1\"\n}"
            },
            "url": {
              "raw": "{{baseUrl}}/users/1/events",
              "host": ["{{baseUrl}}"],
              "path": ["users", "1", "events"]
            }
          },
          "response": []
        },
        {
          "name": "6. Создание события 2 (User 2)",
          "request": {
            "method": "POST",
            "header": [
              {
                "key": "Content-Type",
                "value": "application/json"
              }
            ],
            "body": {
              "mode": "raw",
              "raw": "{\n    \"annotation\": \"Test event 2 annotation for rating testing\",\n    \"category\": 1,\n    \"description\": \"Test event 2 description for rating testing\",\n    \"eventDate\": \"2026-07-23 12:00:00\",\n    \"location\": {\n        \"lat\": 55.7558,\n        \"lon\": 37.6173\n    },\n    \"paid\": false,\n    \"participantLimit\": 0,\n    \"requestModeration\": false,\n    \"title\": \"Test Event 2\"\n}"
            },
            "url": {
              "raw": "{{baseUrl}}/users/2/events",
              "host": ["{{baseUrl}}"],
              "path": ["users", "2", "events"]
            }
          },
          "response": []
        },
        {
          "name": "7. Публикация события 1 (Admin)",
          "request": {
            "method": "PATCH",
            "header": [
              {
                "key": "Content-Type",
                "value": "application/json"
              }
            ],
            "body": {
              "mode": "raw",
              "raw": "{\n    \"stateAction\": \"PUBLISH_EVENT\"\n}"
            },
            "url": {
              "raw": "{{baseUrl}}/admin/events/1",
              "host": ["{{baseUrl}}"],
              "path": ["admin", "events", "1"]
            }
          },
          "response": []
        },
        {
          "name": "8. Публикация события 2 (Admin)",
          "request": {
            "method": "PATCH",
            "header": [
              {
                "key": "Content-Type",
                "value": "application/json"
              }
            ],
            "body": {
              "mode": "raw",
              "raw": "{\n    \"stateAction\": \"PUBLISH_EVENT\"\n}"
            },
            "url": {
              "raw": "{{baseUrl}}/admin/events/2",
              "host": ["{{baseUrl}}"],
              "path": ["admin", "events", "2"]
            }
          },
          "response": []
        }
      ]
    },
    {
      "name": "Тесты рейтингов",
      "item": [
        {
          "name": "9. Создание лайка (User 2 → Event 1)",
          "request": {
            "method": "POST",
            "header": [],
            "url": {
              "raw": "{{baseUrl}}/users/2/ratings/1?isLike=false",
              "host": ["{{baseUrl}}"],
              "path": ["users", "2", "ratings", "1"],
              "query": [
                {
                  "key": "isLike",
                  "value": "false"
                }
              ]
            }
          },
          "response": []
        },
        {
          "name": "10. Создание лайка (User 3 → Event 1)",
          "request": {
            "method": "POST",
            "header": [],
            "url": {
              "raw": "{{baseUrl}}/users/3/ratings/1?isLike=true",
              "host": ["{{baseUrl}}"],
              "path": ["users", "3", "ratings", "1"],
              "query": [
                {
                  "key": "isLike",
                  "value": "true"
                }
              ]
            }
          },
          "response": []
        },
        {
          "name": "11. Получение оценки (User 2 → Event 1)",
          "request": {
            "method": "GET",
            "header": [],
            "url": {
              "raw": "{{baseUrl}}/users/2/ratings/1",
              "host": ["{{baseUrl}}"],
              "path": ["users", "2", "ratings", "1"]
            }
          },
          "response": []
        },
        {
          "name": "12. Обновление оценки (лайк → дизлайк)",
          "request": {
            "method": "POST",
            "header": [],
            "url": {
              "raw": "{{baseUrl}}/users/2/ratings/1?isLike=false",
              "host": ["{{baseUrl}}"],
              "path": ["users", "2", "ratings", "1"],
              "query": [
                {
                  "key": "isLike",
                  "value": "false"
                }
              ]
            }
          },
          "response": []
        },
        {
          "name": "13. Получение статистики рейтинга события 1",
          "request": {
            "method": "GET",
            "header": [],
            "url": {
              "raw": "{{baseUrl}}/users/1/ratings/1/stats",
              "host": ["{{baseUrl}}"],
              "path": ["users", "1", "ratings", "1", "stats"]
            }
          },
          "response": []
        },
        {
          "name": "14. Удаление оценки (User 2 → Event 1)",
          "request": {
            "method": "DELETE",
            "header": [],
            "url": {
              "raw": "{{baseUrl}}/users/2/ratings/1",
              "host": ["{{baseUrl}}"],
              "path": ["users", "2", "ratings", "1"]
            }
          },
          "response": []
        },
        {
          "name": "15. Получение рейтинга пользователя как автора (User 1)",
          "request": {
            "method": "GET",
            "header": [],
            "url": {
              "raw": "{{baseUrl}}/users/1/ratings/user-rating",
              "host": ["{{baseUrl}}"],
              "path": ["users", "1", "ratings", "user-rating"]
            }
          },
          "response": []
        },
        {
          "name": "16. Получение рейтингов нескольких пользователей",
          "request": {
            "method": "GET",
            "header": [],
            "url": {
              "raw": "{{baseUrl}}/users/1/ratings/user-ratings?userIds=1,2,3",
              "host": ["{{baseUrl}}"],
              "path": ["users", "1", "ratings", "user-ratings"],
              "query": [
                {
                  "key": "userIds",
                  "value": "1,2,3"
                }
              ]
            }
          },
          "response": []
        }
      ]
    },
    {
      "name": "Негативные тесты",
      "item": [
        {
          "name": "17. Ошибка - оценка своего события (409 Conflict)",
          "request": {
            "method": "POST",
            "header": [],
            "url": {
              "raw": "{{baseUrl}}/users/1/ratings/1?isLike=true",
              "host": ["{{baseUrl}}"],
              "path": ["users", "1", "ratings", "1"],
              "query": [
                {
                  "key": "isLike",
                  "value": "true"
                }
              ]
            }
          },
          "response": []
        },
        {
          "name": "18. Ошибка - несуществующее событие (404 Not Found)",
          "request": {
            "method": "POST",
            "header": [],
            "url": {
              "raw": "{{baseUrl}}/users/2/ratings/999?isLike=true",
              "host": ["{{baseUrl}}"],
              "path": ["users", "2", "ratings", "999"],
              "query": [
                {
                  "key": "isLike",
                  "value": "true"
                }
              ]
            }
          },
          "response": []
        },
        {
          "name": "19. Ошибка - несуществующий пользователь (404 Not Found)",
          "request": {
            "method": "POST",
            "header": [],
            "url": {
              "raw": "{{baseUrl}}/users/999/ratings/1?isLike=true",
              "host": ["{{baseUrl}}"],
              "path": ["users", "999", "ratings", "1"],
              "query": [
                {
                  "key": "isLike",
                  "value": "true"
                }
              ]
            }
          },
          "response": []
        },
        {
          "name": "20. Ошибка - несуществующая оценка (404 Not Found)",
          "request": {
            "method": "GET",
            "header": [],
            "url": {
              "raw": "{{baseUrl}}/users/1/ratings/999",
              "host": ["{{baseUrl}}"],
              "path": ["users", "1", "ratings", "999"]
            }
          },
          "response": []
        }
      ]
    },
    {
      "name": "Сортировка по рейтингу",
      "item": [
        {
          "name": "21. Получение событий с сортировкой по рейтингу",
          "request": {
            "method": "GET",
            "header": [],
            "url": {
              "raw": "{{baseUrl}}/events?sort=RATING&size=10",
              "host": ["{{baseUrl}}"],
              "path": ["events"],
              "query": [
                {
                  "key": "sort",
                  "value": "RATING"
                },
                {
                  "key": "size",
                  "value": "10"
                }
              ]
            }
          },
          "response": []
        },
        {
          "name": "22. Получение событий с фильтрацией и сортировкой по рейтингу",
          "request": {
            "method": "GET",
            "header": [],
            "url": {
              "raw": "{{baseUrl}}/events?sort=RATING&categories=1&paid=false",
              "host": ["{{baseUrl}}"],
              "path": ["events"],
              "query": [
                {
                  "key": "sort",
                  "value": "RATING"
                },
                {
                  "key": "categories",
                  "value": "1"
                },
                {
                  "key": "paid",
                  "value": "false"
                }
              ]
            }
          },
          "response": []
        }
      ]
    },
    {
      "name": "Очистка данных",
      "item": [
        {
          "name": "23. Удаление всех рейтингов",
          "request": {
            "method": "DELETE",
            "header": [],
            "url": {
              "raw": "{{baseUrl}}/admin/ratings/clear",
              "host": ["{{baseUrl}}"],
              "path": ["admin", "ratings", "clear"]
            }
          },
          "response": []
        },
        {
          "name": "24. Удаление события 1",
          "request": {
            "method": "DELETE",
            "header": [],
            "url": {
              "raw": "{{baseUrl}}/admin/events/1",
              "host": ["{{baseUrl}}"],
              "path": ["admin", "events", "1"]
            }
          },
          "response": []
        },
        {
          "name": "25. Удаление события 2",
          "request": {
            "method": "DELETE",
            "header": [],
            "url": {
              "raw": "{{baseUrl}}/admin/events/2",
              "host": ["{{baseUrl}}"],
              "path": ["admin", "events", "2"]
            }
          },
          "response": []
        },
        {
          "name": "26. Удаление категории",
          "request": {
            "method": "DELETE",
            "header": [],
            "url": {
              "raw": "{{baseUrl}}/admin/categories/1",
              "host": ["{{baseUrl}}"],
              "path": ["admin", "categories", "1"]
            }
          },
          "response": []
        },
        {
          "name": "27. Удаление пользователя 3",
          "request": {
            "method": "DELETE",
            "header": [],
            "url": {
              "raw": "{{baseUrl}}/admin/users/3",
              "host": ["{{baseUrl}}"],
              "path": ["admin", "users", "3"]
            }
          },
          "response": []
        },
        {
          "name": "28. Удаление пользователя 2",
          "request": {
            "method": "DELETE",
            "header": [],
            "url": {
              "raw": "{{baseUrl}}/admin/users/2",
              "host": ["{{baseUrl}}"],
              "path": ["admin", "users", "2"]
            }
          },
          "response": []
        },
        {
          "name": "29. Удаление пользователя 1",
          "request": {
            "method": "DELETE",
            "header": [],
            "url": {
              "raw": "{{baseUrl}}/admin/users/1",
              "host": ["{{baseUrl}}"],
              "path": ["admin", "users", "1"]
            }
          },
          "response": []
        }
      ]
    }
  ],
  "variable": [
    {
      "key": "baseUrl",
      "value": "http://localhost:8080"
    }
  ]
}